{
  "source": "cmp_components_b.md",
  "source_hash": "629e0e55cda6d9b2e656147c2db2f7de",
  "translated_at": "2026-03-26",
  "items": [
    {
      "id": 1,
      "br": "Visão Geral",
      "en": "Overview",
      "es": "Vision General"
    },
    {
      "id": 2,
      "br": "Armazena os componentes de compensação (salary, bonus, stock, allowance, etc.) que formam o pacote de remuneração total. Cada componente define um tipo de remuneração configurável.",
      "en": "Stores the compensation components (salary, bonus, stock, allowance, etc.) that form the total remuneration package. Each component defines a configurable remuneration type.",
      "es": "Almacena los componentes de compensacion (salary, bonus, stock, allowance, etc.) que forman el paquete de remuneracion total. Cada componente define un tipo de remuneracion configurable."
    },
    {
      "id": 3,
      "br": "Sufixo _B",
      "en": "Suffix _B",
      "es": "Sufijo _B"
    },
    {
      "id": 4,
      "br": "O sufixo _B indica tabela base (dados técnicos) — a tabela de traduções correspondente (_TL) contém os textos traduzidos.",
      "en": "The _B suffix indicates a base table (technical data) — the corresponding translations table (_TL) contains the translated texts.",
      "es": "El sufijo _B indica tabla base (datos tecnicos) — la tabla de traducciones correspondiente (_TL) contiene los textos traducidos."
    },
    {
      "id": 5,
      "br": "Propósito de Negócio",
      "en": "Business Purpose",
      "es": "Proposito de Negocio"
    },
    {
      "id": 6,
      "br": "Esta tabela é utilizada nos seguintes processos:",
      "en": "This table is used in the following processes:",
      "es": "Esta tabla se utiliza en los siguientes procesos:"
    },
    {
      "id": 7,
      "br": "Define os componentes do pacote de compensação.",
      "en": "Defines the components of the compensation package.",
      "es": "Define los componentes del paquete de compensacion."
    },
    {
      "id": 8,
      "br": "Cada componente tem regras, frequência e moeda.",
      "en": "Each component has rules, frequency, and currency.",
      "es": "Cada componente tiene reglas, frecuencia y moneda."
    },
    {
      "id": 9,
      "br": "Base para Total Compensation Statements.",
      "en": "Basis for Total Compensation Statements.",
      "es": "Base para Total Compensation Statements."
    },
    {
      "id": 10,
      "br": "Usado no CWB para distribuição de componentes específicos.",
      "en": "Used in CWB for distribution of specific components.",
      "es": "Usado en CWB para distribucion de componentes especificos."
    },
    {
      "id": 11,
      "br": "Colunas Principais",
      "en": "Main Columns",
      "es": "Columnas Principales"
    },
    {
      "id": 12,
      "br": "Confiança",
      "en": "Confidence",
      "es": "Confianza"
    },
    {
      "id": 13,
      "br": "Escala de 0% a 100% — grau de certeza da descrição gerada por IA com base na documentação oficial Oracle (OEDMF/BICC Release 13/25A).",
      "en": "Scale from 0% to 100% — degree of certainty of the AI-generated description based on official Oracle documentation (OEDMF/BICC Release 13/25A).",
      "es": "Escala de 0% a 100% — grado de certeza de la descripcion generada por IA con base en la documentacion oficial Oracle (OEDMF/BICC Release 13/25A)."
    },
    {
      "id": 14,
      "br": "- 🟢 81–100% — Coluna presente na documentação oficial Oracle; nome, tipo e descrição confirmados.",
      "en": "- 🟢 81–100% — Column present in official Oracle documentation; name, type, and description confirmed.",
      "es": "- 🟢 81–100% — Columna presente en la documentacion oficial Oracle; nombre, tipo y descripcion confirmados."
    },
    {
      "id": 15,
      "br": "- 🟡 51–80% — Coluna inferida por naming convention ou padrão Oracle; tipo exato pode variar.",
      "en": "- 🟡 51–80% — Column inferred by naming convention or Oracle standard; exact type may vary.",
      "es": "- 🟡 51–80% — Columna inferida por naming convention o estandar Oracle; tipo exacto puede variar."
    },
    {
      "id": 16,
      "br": "- 🔴 0–50% — Existência ou tipo incertos; pode não existir no release atual; validar no ambiente.",
      "en": "- 🔴 0–50% — Existence or type uncertain; may not exist in the current release; validate in the environment.",
      "es": "- 🔴 0–50% — Existencia o tipo inciertos; puede no existir en el release actual; validar en el ambiente."
    },
    {
      "id": 17,
      "br": "Coluna",
      "en": "Column",
      "es": "Columna"
    },
    {
      "id": 18,
      "br": "Tipo",
      "en": "Type",
      "es": "Tipo"
    },
    {
      "id": 19,
      "br": "Nulo?",
      "en": "Nullable?",
      "es": "Nulo?"
    },
    {
      "id": 20,
      "br": "Categoria",
      "en": "Category",
      "es": "Categoria"
    },
    {
      "id": 21,
      "br": "Descrição",
      "en": "Description",
      "es": "Descripcion"
    },
    {
      "id": 22,
      "br": "Identificador único do componente",
      "en": "Unique component identifier",
      "es": "Identificador unico del componente"
    },
    {
      "id": 23,
      "br": "Código",
      "en": "Code",
      "es": "Codigo"
    },
    {
      "id": 24,
      "br": "Código do componente",
      "en": "Component code",
      "es": "Codigo del componente"
    },
    {
      "id": 25,
      "br": "Classificação",
      "en": "Classification",
      "es": "Clasificacion"
    },
    {
      "id": 26,
      "br": "Tipo (SALARY, BONUS, STOCK, ALLOWANCE)",
      "en": "Type (SALARY, BONUS, STOCK, ALLOWANCE)",
      "es": "Tipo (SALARY, BONUS, STOCK, ALLOWANCE)"
    },
    {
      "id": 27,
      "br": "Configuração",
      "en": "Configuration",
      "es": "Configuracion"
    },
    {
      "id": 28,
      "br": "Frequência (ANNUAL, MONTHLY, ONE_TIME)",
      "en": "Frequency (ANNUAL, MONTHLY, ONE_TIME)",
      "es": "Frecuencia (ANNUAL, MONTHLY, ONE_TIME)"
    },
    {
      "id": 29,
      "br": "Financeiro",
      "en": "Financial",
      "es": "Financiero"
    },
    {
      "id": 30,
      "br": "Moeda padrão do componente",
      "en": "Default component currency",
      "es": "Moneda predeterminada del componente"
    },
    {
      "id": 31,
      "br": "Status (ACTIVE, INACTIVE)",
      "en": "Status (ACTIVE, INACTIVE)",
      "es": "Estado (ACTIVE, INACTIVE)"
    },
    {
      "id": 32,
      "br": "Auditoria",
      "en": "Audit",
      "es": "Auditoria"
    },
    {
      "id": 33,
      "br": "Usuário que criou",
      "en": "Created by user",
      "es": "Usuario que creo"
    },
    {
      "id": 34,
      "br": "Data/hora de criação",
      "en": "Creation date/time",
      "es": "Fecha/hora de creacion"
    },
    {
      "id": 35,
      "br": "Último que alterou",
      "en": "Last modified by",
      "es": "Ultimo que modifico"
    },
    {
      "id": 36,
      "br": "Data/hora da última alteração",
      "en": "Last modification date/time",
      "es": "Fecha/hora de la ultima modificacion"
    },
    {
      "id": 37,
      "br": "Controle",
      "en": "Control",
      "es": "Control"
    },
    {
      "id": 38,
      "br": "Controle de versão otimista",
      "en": "Optimistic version control",
      "es": "Control de version optimista"
    },
    {
      "id": 39,
      "br": "Relacionamentos",
      "en": "Relationships",
      "es": "Relaciones"
    },
    {
      "id": 40,
      "br": "Tabelas-pai (FK de entrada)",
      "en": "Parent Tables (Inbound FK)",
      "es": "Tablas padre (FK de entrada)"
    },
    {
      "id": 41,
      "br": "Nenhuma FK de entrada direta (tabela de configuração raiz).",
      "en": "No direct inbound FK (root configuration table).",
      "es": "Ninguna FK de entrada directa (tabla de configuracion raiz)."
    },
    {
      "id": 42,
      "br": "Tabelas-filha (FK de saída)",
      "en": "Child Tables (Outbound FK)",
      "es": "Tablas hija (FK de salida)"
    },
    {
      "id": 43,
      "br": "traduções",
      "en": "translations",
      "es": "traducciones"
    },
    {
      "id": 44,
      "br": "valores por pessoa",
      "en": "values per person",
      "es": "valores por persona"
    },
    {
      "id": 45,
      "br": "Uso Típico",
      "en": "Typical Usage",
      "es": "Uso Tipico"
    },
    {
      "id": 46,
      "br": "Componentes ativos por tipo",
      "en": "Active components by type",
      "es": "Componentes activos por tipo"
    },
    {
      "id": 47,
      "br": "Filtros comuns",
      "en": "Common Filters",
      "es": "Filtros comunes"
    },
    {
      "id": 48,
      "br": "Componentes ativos",
      "en": "Active components",
      "es": "Componentes activos"
    },
    {
      "id": 49,
      "br": "Componentes salariais",
      "en": "Salary components",
      "es": "Componentes salariales"
    },
    {
      "id": 50,
      "br": "Componentes de bônus",
      "en": "Bonus components",
      "es": "Componentes de bonus"
    },
    {
      "id": 51,
      "br": "Observações",
      "en": "Notes",
      "es": "Observaciones"
    },
    {
      "id": 52,
      "br": "Tabela base (_B): traduções estão em CMP_COMPONENTS_TL.",
      "en": "Base table (_B): translations are in CMP_COMPONENTS_TL.",
      "es": "Tabla base (_B): traducciones estan en CMP_COMPONENTS_TL."
    },
    {
      "id": 53,
      "br": "O tipo determina o comportamento do componente no cálculo de compensação total.",
      "en": "The type determines the component behavior in total compensation calculation.",
      "es": "El tipo determina el comportamiento del componente en el calculo de compensacion total."
    },
    {
      "id": 54,
      "br": "Componentes ONE_TIME são para pagamentos únicos (ex.: bônus de contratação).",
      "en": "ONE_TIME components are for one-time payments (e.g., hiring bonus).",
      "es": "Los componentes ONE_TIME son para pagos unicos (ej.: bonus de contratacion)."
    },
    {
      "id": 55,
      "br": "Referências",
      "en": "References",
      "es": "Referencias"
    },
    {
      "id": 56,
      "br": "[Oracle Docs — CMP_COMPONENTS_B](https://docs.oracle.com/en/cloud/saas/human-resources/25a/oedmf/cmpcomponentsb.html)",
      "en": "[Oracle Docs — CMP_COMPONENTS_B](https://docs.oracle.com/en/cloud/saas/human-resources/25a/oedmf/cmpcomponentsb.html)",
      "es": "[Oracle Docs — CMP_COMPONENTS_B](https://docs.oracle.com/en/cloud/saas/human-resources/25a/oedmf/cmpcomponentsb.html)"
    },
    {
      "id": 57,
      "br": "Dossiê do módulo HCM",
      "en": "HCM Module Dossier",
      "es": "Dossier del modulo HCM"
    }
  ]
}
