{
  "meta": {
    "pvo_name": "JournalEncumbranceTLExtractPVO",
    "full_path": "FscmTopModelAM.FinExtractAM.GlBiccExtractAM.JournalEncumbranceTLExtractPVO",
    "module_path": "FscmTopModelAM.FinExtractAM.GlBiccExtractAM",
    "module_code": "OTHER",
    "type": "pvo",
    "description": "View Object para extração BICC de dados de Journal Encumbrance TLExtract. Acessa as tabelas: GL_ENCUMBRANCE_TYPES_TL."
  },
  "stats": {
    "total_attributes": 12,
    "tables_count": 1,
    "bicc_enabled": 12,
    "bicc_pct": 100,
    "pk_count": 2
  },
  "tables": [
    "GL_ENCUMBRANCE_TYPES_TL"
  ],
  "attributes": [
    {
      "name": "JournalEncumbranceTLPEOCreatedBy",
      "table": "GL_ENCUMBRANCE_TYPES_TL",
      "column": "CREATED_BY",
      "bicc": true,
      "pk": false,
      "incremental": false
    },
    {
      "name": "JournalEncumbranceTLPEOCreationDate",
      "table": "GL_ENCUMBRANCE_TYPES_TL",
      "column": "CREATION_DATE",
      "bicc": true,
      "pk": false,
      "incremental": false
    },
    {
      "name": "JournalEncumbranceTLPEODescription",
      "table": "GL_ENCUMBRANCE_TYPES_TL",
      "column": "DESCRIPTION",
      "bicc": true,
      "pk": false,
      "incremental": false
    },
    {
      "name": "JournalEncumbranceTLPEOEncumbranceType",
      "table": "GL_ENCUMBRANCE_TYPES_TL",
      "column": "ENCUMBRANCE_TYPE",
      "bicc": true,
      "pk": false,
      "incremental": false
    },
    {
      "name": "JournalEncumbranceTLPEOEncumbranceTypeId",
      "table": "GL_ENCUMBRANCE_TYPES_TL",
      "column": "ENCUMBRANCE_TYPE_ID",
      "bicc": true,
      "pk": true,
      "incremental": false
    },
    {
      "name": "JournalEncumbranceTLPEOLanguage",
      "table": "GL_ENCUMBRANCE_TYPES_TL",
      "column": "LANGUAGE",
      "bicc": true,
      "pk": true,
      "incremental": false
    },
    {
      "name": "JournalEncumbranceTLPEOLastUpdateDate",
      "table": "GL_ENCUMBRANCE_TYPES_TL",
      "column": "LAST_UPDATE_DATE",
      "bicc": true,
      "pk": false,
      "incremental": true
    },
    {
      "name": "JournalEncumbranceTLPEOLastUpdateLogin",
      "table": "GL_ENCUMBRANCE_TYPES_TL",
      "column": "LAST_UPDATE_LOGIN",
      "bicc": true,
      "pk": false,
      "incremental": false
    },
    {
      "name": "JournalEncumbranceTLPEOLastUpdatedBy",
      "table": "GL_ENCUMBRANCE_TYPES_TL",
      "column": "LAST_UPDATED_BY",
      "bicc": true,
      "pk": false,
      "incremental": false
    },
    {
      "name": "JournalEncumbranceTLPEOObjectVersionNumber",
      "table": "GL_ENCUMBRANCE_TYPES_TL",
      "column": "OBJECT_VERSION_NUMBER",
      "bicc": true,
      "pk": false,
      "incremental": false
    },
    {
      "name": "JournalEncumbranceTLPEOSeedDataSource",
      "table": "GL_ENCUMBRANCE_TYPES_TL",
      "column": "SEED_DATA_SOURCE",
      "bicc": true,
      "pk": false,
      "incremental": false
    },
    {
      "name": "JournalEncumbranceTLPEOSourceLang",
      "table": "GL_ENCUMBRANCE_TYPES_TL",
      "column": "SOURCE_LANG",
      "bicc": true,
      "pk": false,
      "incremental": false
    }
  ],
  "by_table": {
    "GL_ENCUMBRANCE_TYPES_TL": [
      {
        "attribute": "JournalEncumbranceTLPEOCreatedBy",
        "column": "CREATED_BY",
        "bicc": true,
        "pk": false
      },
      {
        "attribute": "JournalEncumbranceTLPEOCreationDate",
        "column": "CREATION_DATE",
        "bicc": true,
        "pk": false
      },
      {
        "attribute": "JournalEncumbranceTLPEODescription",
        "column": "DESCRIPTION",
        "bicc": true,
        "pk": false
      },
      {
        "attribute": "JournalEncumbranceTLPEOEncumbranceType",
        "column": "ENCUMBRANCE_TYPE",
        "bicc": true,
        "pk": false
      },
      {
        "attribute": "JournalEncumbranceTLPEOEncumbranceTypeId",
        "column": "ENCUMBRANCE_TYPE_ID",
        "bicc": true,
        "pk": true
      },
      {
        "attribute": "JournalEncumbranceTLPEOLanguage",
        "column": "LANGUAGE",
        "bicc": true,
        "pk": true
      },
      {
        "attribute": "JournalEncumbranceTLPEOLastUpdateDate",
        "column": "LAST_UPDATE_DATE",
        "bicc": true,
        "pk": false
      },
      {
        "attribute": "JournalEncumbranceTLPEOLastUpdateLogin",
        "column": "LAST_UPDATE_LOGIN",
        "bicc": true,
        "pk": false
      },
      {
        "attribute": "JournalEncumbranceTLPEOLastUpdatedBy",
        "column": "LAST_UPDATED_BY",
        "bicc": true,
        "pk": false
      },
      {
        "attribute": "JournalEncumbranceTLPEOObjectVersionNumber",
        "column": "OBJECT_VERSION_NUMBER",
        "bicc": true,
        "pk": false
      },
      {
        "attribute": "JournalEncumbranceTLPEOSeedDataSource",
        "column": "SEED_DATA_SOURCE",
        "bicc": true,
        "pk": false
      },
      {
        "attribute": "JournalEncumbranceTLPEOSourceLang",
        "column": "SOURCE_LANG",
        "bicc": true,
        "pk": false
      }
    ]
  }
}