{
  "meta": {
    "pvo_name": "OrganizationHierarchyExtractPVO",
    "full_path": "FscmTopModelAM.PrjExtractAM.PjfBiccExtractAM.OrganizationHierarchyExtractPVO",
    "module_path": "FscmTopModelAM.PrjExtractAM.PjfBiccExtractAM",
    "module_code": "OTHER",
    "type": "pvo",
    "description": "View Object para extração BICC de dados de Organization Hierarchy Extract. Acessa as tabelas: PJF_ORG_HIERARCHY_DENORM."
  },
  "stats": {
    "total_attributes": 13,
    "tables_count": 1,
    "bicc_enabled": 13,
    "bicc_pct": 100,
    "pk_count": 5
  },
  "tables": [
    "PJF_ORG_HIERARCHY_DENORM"
  ],
  "attributes": [
    {
      "name": "OrganizationHierarchyPEOChildLevel",
      "table": "PJF_ORG_HIERARCHY_DENORM",
      "column": "CHILD_LEVEL",
      "bicc": true,
      "pk": false,
      "incremental": false
    },
    {
      "name": "OrganizationHierarchyPEOChildOrganizationId",
      "table": "PJF_ORG_HIERARCHY_DENORM",
      "column": "CHILD_ORGANIZATION_ID",
      "bicc": true,
      "pk": true,
      "incremental": false
    },
    {
      "name": "OrganizationHierarchyPEOCreatedBy",
      "table": "PJF_ORG_HIERARCHY_DENORM",
      "column": "CREATED_BY",
      "bicc": true,
      "pk": false,
      "incremental": false
    },
    {
      "name": "OrganizationHierarchyPEOCreationDate",
      "table": "PJF_ORG_HIERARCHY_DENORM",
      "column": "CREATION_DATE",
      "bicc": true,
      "pk": false,
      "incremental": false
    },
    {
      "name": "OrganizationHierarchyPEOLastUpdateDate",
      "table": "PJF_ORG_HIERARCHY_DENORM",
      "column": "LAST_UPDATE_DATE",
      "bicc": true,
      "pk": false,
      "incremental": true
    },
    {
      "name": "OrganizationHierarchyPEOLastUpdateLogin",
      "table": "PJF_ORG_HIERARCHY_DENORM",
      "column": "LAST_UPDATE_LOGIN",
      "bicc": true,
      "pk": false,
      "incremental": false
    },
    {
      "name": "OrganizationHierarchyPEOLastUpdatedBy",
      "table": "PJF_ORG_HIERARCHY_DENORM",
      "column": "LAST_UPDATED_BY",
      "bicc": true,
      "pk": false,
      "incremental": false
    },
    {
      "name": "OrganizationHierarchyPEOObjectVersionNumber",
      "table": "PJF_ORG_HIERARCHY_DENORM",
      "column": "OBJECT_VERSION_NUMBER",
      "bicc": true,
      "pk": false,
      "incremental": false
    },
    {
      "name": "OrganizationHierarchyPEOParentLevel",
      "table": "PJF_ORG_HIERARCHY_DENORM",
      "column": "PARENT_LEVEL",
      "bicc": true,
      "pk": false,
      "incremental": false
    },
    {
      "name": "OrganizationHierarchyPEOParentOrganizationId",
      "table": "PJF_ORG_HIERARCHY_DENORM",
      "column": "PARENT_ORGANIZATION_ID",
      "bicc": true,
      "pk": true,
      "incremental": false
    },
    {
      "name": "OrganizationHierarchyPEOTreeCode",
      "table": "PJF_ORG_HIERARCHY_DENORM",
      "column": "TREE_CODE",
      "bicc": true,
      "pk": true,
      "incremental": false
    },
    {
      "name": "OrganizationHierarchyPEOTreeStructureCode",
      "table": "PJF_ORG_HIERARCHY_DENORM",
      "column": "TREE_STRUCTURE_CODE",
      "bicc": true,
      "pk": true,
      "incremental": false
    },
    {
      "name": "OrganizationHierarchyPEOTreeVersionId",
      "table": "PJF_ORG_HIERARCHY_DENORM",
      "column": "TREE_VERSION_ID",
      "bicc": true,
      "pk": true,
      "incremental": false
    }
  ],
  "by_table": {
    "PJF_ORG_HIERARCHY_DENORM": [
      {
        "attribute": "OrganizationHierarchyPEOChildLevel",
        "column": "CHILD_LEVEL",
        "bicc": true,
        "pk": false
      },
      {
        "attribute": "OrganizationHierarchyPEOChildOrganizationId",
        "column": "CHILD_ORGANIZATION_ID",
        "bicc": true,
        "pk": true
      },
      {
        "attribute": "OrganizationHierarchyPEOCreatedBy",
        "column": "CREATED_BY",
        "bicc": true,
        "pk": false
      },
      {
        "attribute": "OrganizationHierarchyPEOCreationDate",
        "column": "CREATION_DATE",
        "bicc": true,
        "pk": false
      },
      {
        "attribute": "OrganizationHierarchyPEOLastUpdateDate",
        "column": "LAST_UPDATE_DATE",
        "bicc": true,
        "pk": false
      },
      {
        "attribute": "OrganizationHierarchyPEOLastUpdateLogin",
        "column": "LAST_UPDATE_LOGIN",
        "bicc": true,
        "pk": false
      },
      {
        "attribute": "OrganizationHierarchyPEOLastUpdatedBy",
        "column": "LAST_UPDATED_BY",
        "bicc": true,
        "pk": false
      },
      {
        "attribute": "OrganizationHierarchyPEOObjectVersionNumber",
        "column": "OBJECT_VERSION_NUMBER",
        "bicc": true,
        "pk": false
      },
      {
        "attribute": "OrganizationHierarchyPEOParentLevel",
        "column": "PARENT_LEVEL",
        "bicc": true,
        "pk": false
      },
      {
        "attribute": "OrganizationHierarchyPEOParentOrganizationId",
        "column": "PARENT_ORGANIZATION_ID",
        "bicc": true,
        "pk": true
      },
      {
        "attribute": "OrganizationHierarchyPEOTreeCode",
        "column": "TREE_CODE",
        "bicc": true,
        "pk": true
      },
      {
        "attribute": "OrganizationHierarchyPEOTreeStructureCode",
        "column": "TREE_STRUCTURE_CODE",
        "bicc": true,
        "pk": true
      },
      {
        "attribute": "OrganizationHierarchyPEOTreeVersionId",
        "column": "TREE_VERSION_ID",
        "bicc": true,
        "pk": true
      }
    ]
  }
}