{
  "meta": {
    "pvo_name": "PjtEventCategoryTypeLookupsPVO",
    "full_path": "FscmTopModelAM.PjrReportingAM.PjtEventCategoryTypeLookupsPVO",
    "module_path": "FscmTopModelAM.PjrReportingAM",
    "module_code": "OTHER",
    "type": "pvo",
    "description": "View Object para extração BICC de dados de Pjt Event Category Type Lookups. Acessa as tabelas: PJT_LOOKUPS."
  },
  "stats": {
    "total_attributes": 27,
    "tables_count": 1,
    "bicc_enabled": 4,
    "bicc_pct": 15,
    "pk_count": 2
  },
  "tables": [
    "PJT_LOOKUPS"
  ],
  "attributes": [
    {
      "name": "LookupCode",
      "table": "PJT_LOOKUPS",
      "column": "LOOKUP_CODE",
      "bicc": true,
      "pk": true,
      "incremental": false
    },
    {
      "name": "LookupType",
      "table": "PJT_LOOKUPS",
      "column": "LOOKUP_TYPE",
      "bicc": true,
      "pk": true,
      "incremental": false
    },
    {
      "name": "PjtLookupsPEOAttribute1",
      "table": "PJT_LOOKUPS",
      "column": "ATTRIBUTE1",
      "bicc": false,
      "pk": false,
      "incremental": false
    },
    {
      "name": "PjtLookupsPEOAttribute10",
      "table": "PJT_LOOKUPS",
      "column": "ATTRIBUTE10",
      "bicc": false,
      "pk": false,
      "incremental": false
    },
    {
      "name": "PjtLookupsPEOAttribute11",
      "table": "PJT_LOOKUPS",
      "column": "ATTRIBUTE11",
      "bicc": false,
      "pk": false,
      "incremental": false
    },
    {
      "name": "PjtLookupsPEOAttribute12",
      "table": "PJT_LOOKUPS",
      "column": "ATTRIBUTE12",
      "bicc": false,
      "pk": false,
      "incremental": false
    },
    {
      "name": "PjtLookupsPEOAttribute13",
      "table": "PJT_LOOKUPS",
      "column": "ATTRIBUTE13",
      "bicc": false,
      "pk": false,
      "incremental": false
    },
    {
      "name": "PjtLookupsPEOAttribute14",
      "table": "PJT_LOOKUPS",
      "column": "ATTRIBUTE14",
      "bicc": false,
      "pk": false,
      "incremental": false
    },
    {
      "name": "PjtLookupsPEOAttribute15",
      "table": "PJT_LOOKUPS",
      "column": "ATTRIBUTE15",
      "bicc": false,
      "pk": false,
      "incremental": false
    },
    {
      "name": "PjtLookupsPEOAttribute2",
      "table": "PJT_LOOKUPS",
      "column": "ATTRIBUTE2",
      "bicc": false,
      "pk": false,
      "incremental": false
    },
    {
      "name": "PjtLookupsPEOAttribute3",
      "table": "PJT_LOOKUPS",
      "column": "ATTRIBUTE3",
      "bicc": false,
      "pk": false,
      "incremental": false
    },
    {
      "name": "PjtLookupsPEOAttribute4",
      "table": "PJT_LOOKUPS",
      "column": "ATTRIBUTE4",
      "bicc": false,
      "pk": false,
      "incremental": false
    },
    {
      "name": "PjtLookupsPEOAttribute5",
      "table": "PJT_LOOKUPS",
      "column": "ATTRIBUTE5",
      "bicc": false,
      "pk": false,
      "incremental": false
    },
    {
      "name": "PjtLookupsPEOAttribute6",
      "table": "PJT_LOOKUPS",
      "column": "ATTRIBUTE6",
      "bicc": false,
      "pk": false,
      "incremental": false
    },
    {
      "name": "PjtLookupsPEOAttribute7",
      "table": "PJT_LOOKUPS",
      "column": "ATTRIBUTE7",
      "bicc": false,
      "pk": false,
      "incremental": false
    },
    {
      "name": "PjtLookupsPEOAttribute8",
      "table": "PJT_LOOKUPS",
      "column": "ATTRIBUTE8",
      "bicc": false,
      "pk": false,
      "incremental": false
    },
    {
      "name": "PjtLookupsPEOAttribute9",
      "table": "PJT_LOOKUPS",
      "column": "ATTRIBUTE9",
      "bicc": false,
      "pk": false,
      "incremental": false
    },
    {
      "name": "PjtLookupsPEOAttributeCategory",
      "table": "PJT_LOOKUPS",
      "column": "ATTRIBUTE_CATEGORY",
      "bicc": false,
      "pk": false,
      "incremental": false
    },
    {
      "name": "PjtLookupsPEODescription",
      "table": "PJT_LOOKUPS",
      "column": "DESCRIPTION",
      "bicc": true,
      "pk": false,
      "incremental": false
    },
    {
      "name": "PjtLookupsPEODisplaySequence",
      "table": "PJT_LOOKUPS",
      "column": "DISPLAY_SEQUENCE",
      "bicc": false,
      "pk": false,
      "incremental": false
    },
    {
      "name": "PjtLookupsPEOEnabledFlag",
      "table": "PJT_LOOKUPS",
      "column": "ENABLED_FLAG",
      "bicc": false,
      "pk": false,
      "incremental": false
    },
    {
      "name": "PjtLookupsPEOEndDateActive",
      "table": "PJT_LOOKUPS",
      "column": "END_DATE_ACTIVE",
      "bicc": false,
      "pk": false,
      "incremental": false
    },
    {
      "name": "PjtLookupsPEOMeaning",
      "table": "PJT_LOOKUPS",
      "column": "MEANING",
      "bicc": true,
      "pk": false,
      "incremental": false
    },
    {
      "name": "PjtLookupsPEOSetId",
      "table": "PJT_LOOKUPS",
      "column": "SET_ID",
      "bicc": false,
      "pk": false,
      "incremental": false
    },
    {
      "name": "PjtLookupsPEOStartDateActive",
      "table": "PJT_LOOKUPS",
      "column": "START_DATE_ACTIVE",
      "bicc": false,
      "pk": false,
      "incremental": false
    },
    {
      "name": "PjtLookupsPEOTag",
      "table": "PJT_LOOKUPS",
      "column": "TAG",
      "bicc": false,
      "pk": false,
      "incremental": false
    },
    {
      "name": "PjtLookupsPEOViewApplicationId",
      "table": "PJT_LOOKUPS",
      "column": "VIEW_APPLICATION_ID",
      "bicc": false,
      "pk": false,
      "incremental": false
    }
  ],
  "by_table": {
    "PJT_LOOKUPS": [
      {
        "attribute": "LookupCode",
        "column": "LOOKUP_CODE",
        "bicc": true,
        "pk": true
      },
      {
        "attribute": "LookupType",
        "column": "LOOKUP_TYPE",
        "bicc": true,
        "pk": true
      },
      {
        "attribute": "PjtLookupsPEOAttribute1",
        "column": "ATTRIBUTE1",
        "bicc": false,
        "pk": false
      },
      {
        "attribute": "PjtLookupsPEOAttribute10",
        "column": "ATTRIBUTE10",
        "bicc": false,
        "pk": false
      },
      {
        "attribute": "PjtLookupsPEOAttribute11",
        "column": "ATTRIBUTE11",
        "bicc": false,
        "pk": false
      },
      {
        "attribute": "PjtLookupsPEOAttribute12",
        "column": "ATTRIBUTE12",
        "bicc": false,
        "pk": false
      },
      {
        "attribute": "PjtLookupsPEOAttribute13",
        "column": "ATTRIBUTE13",
        "bicc": false,
        "pk": false
      },
      {
        "attribute": "PjtLookupsPEOAttribute14",
        "column": "ATTRIBUTE14",
        "bicc": false,
        "pk": false
      },
      {
        "attribute": "PjtLookupsPEOAttribute15",
        "column": "ATTRIBUTE15",
        "bicc": false,
        "pk": false
      },
      {
        "attribute": "PjtLookupsPEOAttribute2",
        "column": "ATTRIBUTE2",
        "bicc": false,
        "pk": false
      },
      {
        "attribute": "PjtLookupsPEOAttribute3",
        "column": "ATTRIBUTE3",
        "bicc": false,
        "pk": false
      },
      {
        "attribute": "PjtLookupsPEOAttribute4",
        "column": "ATTRIBUTE4",
        "bicc": false,
        "pk": false
      },
      {
        "attribute": "PjtLookupsPEOAttribute5",
        "column": "ATTRIBUTE5",
        "bicc": false,
        "pk": false
      },
      {
        "attribute": "PjtLookupsPEOAttribute6",
        "column": "ATTRIBUTE6",
        "bicc": false,
        "pk": false
      },
      {
        "attribute": "PjtLookupsPEOAttribute7",
        "column": "ATTRIBUTE7",
        "bicc": false,
        "pk": false
      },
      {
        "attribute": "PjtLookupsPEOAttribute8",
        "column": "ATTRIBUTE8",
        "bicc": false,
        "pk": false
      },
      {
        "attribute": "PjtLookupsPEOAttribute9",
        "column": "ATTRIBUTE9",
        "bicc": false,
        "pk": false
      },
      {
        "attribute": "PjtLookupsPEOAttributeCategory",
        "column": "ATTRIBUTE_CATEGORY",
        "bicc": false,
        "pk": false
      },
      {
        "attribute": "PjtLookupsPEODescription",
        "column": "DESCRIPTION",
        "bicc": true,
        "pk": false
      },
      {
        "attribute": "PjtLookupsPEODisplaySequence",
        "column": "DISPLAY_SEQUENCE",
        "bicc": false,
        "pk": false
      },
      {
        "attribute": "PjtLookupsPEOEnabledFlag",
        "column": "ENABLED_FLAG",
        "bicc": false,
        "pk": false
      },
      {
        "attribute": "PjtLookupsPEOEndDateActive",
        "column": "END_DATE_ACTIVE",
        "bicc": false,
        "pk": false
      },
      {
        "attribute": "PjtLookupsPEOMeaning",
        "column": "MEANING",
        "bicc": true,
        "pk": false
      },
      {
        "attribute": "PjtLookupsPEOSetId",
        "column": "SET_ID",
        "bicc": false,
        "pk": false
      },
      {
        "attribute": "PjtLookupsPEOStartDateActive",
        "column": "START_DATE_ACTIVE",
        "bicc": false,
        "pk": false
      },
      {
        "attribute": "PjtLookupsPEOTag",
        "column": "TAG",
        "bicc": false,
        "pk": false
      },
      {
        "attribute": "PjtLookupsPEOViewApplicationId",
        "column": "VIEW_APPLICATION_ID",
        "bicc": false,
        "pk": false
      }
    ]
  }
}