{
  "meta": {
    "pvo_name": "SourceSystemBase",
    "full_path": "FscmTopModelAM.EgiBatchesPublicModelAnalyticsAM.SourceSystemBase",
    "module_path": "FscmTopModelAM.EgiBatchesPublicModelAnalyticsAM",
    "module_code": "OTHER",
    "type": "pvo",
    "description": "View Object para extração BICC de dados de Source System Base. Acessa as tabelas: HZ_ORIG_SYSTEMS_B."
  },
  "stats": {
    "total_attributes": 17,
    "tables_count": 1,
    "bicc_enabled": 7,
    "bicc_pct": 41,
    "pk_count": 1
  },
  "tables": [
    "HZ_ORIG_SYSTEMS_B"
  ],
  "attributes": [
    {
      "name": "CreatedBy",
      "table": "HZ_ORIG_SYSTEMS_B",
      "column": "CREATED_BY",
      "bicc": true,
      "pk": false,
      "incremental": false
    },
    {
      "name": "CreatedByModule",
      "table": "HZ_ORIG_SYSTEMS_B",
      "column": "CREATED_BY_MODULE",
      "bicc": false,
      "pk": false,
      "incremental": false
    },
    {
      "name": "CreationDate",
      "table": "HZ_ORIG_SYSTEMS_B",
      "column": "CREATION_DATE",
      "bicc": true,
      "pk": false,
      "incremental": false
    },
    {
      "name": "EnableForItemsFlag",
      "table": "HZ_ORIG_SYSTEMS_B",
      "column": "ENABLE_FOR_ITEMS_FLAG",
      "bicc": false,
      "pk": false,
      "incremental": false
    },
    {
      "name": "EnableForPlanningFlag",
      "table": "HZ_ORIG_SYSTEMS_B",
      "column": "ENABLE_FOR_PLANNING_FLAG",
      "bicc": false,
      "pk": false,
      "incremental": false
    },
    {
      "name": "EnableForTcaFlag",
      "table": "HZ_ORIG_SYSTEMS_B",
      "column": "ENABLE_FOR_TCA_FLAG",
      "bicc": false,
      "pk": false,
      "incremental": false
    },
    {
      "name": "EndDateActive",
      "table": "HZ_ORIG_SYSTEMS_B",
      "column": "END_DATE_ACTIVE",
      "bicc": false,
      "pk": false,
      "incremental": false
    },
    {
      "name": "LastUpdateDate",
      "table": "HZ_ORIG_SYSTEMS_B",
      "column": "LAST_UPDATE_DATE",
      "bicc": true,
      "pk": false,
      "incremental": true
    },
    {
      "name": "LastUpdateLogin",
      "table": "HZ_ORIG_SYSTEMS_B",
      "column": "LAST_UPDATE_LOGIN",
      "bicc": false,
      "pk": false,
      "incremental": false
    },
    {
      "name": "LastUpdatedBy",
      "table": "HZ_ORIG_SYSTEMS_B",
      "column": "LAST_UPDATED_BY",
      "bicc": true,
      "pk": false,
      "incremental": false
    },
    {
      "name": "ObjectVersionNumber",
      "table": "HZ_ORIG_SYSTEMS_B",
      "column": "OBJECT_VERSION_NUMBER",
      "bicc": false,
      "pk": false,
      "incremental": false
    },
    {
      "name": "OrigSystem",
      "table": "HZ_ORIG_SYSTEMS_B",
      "column": "ORIG_SYSTEM",
      "bicc": true,
      "pk": false,
      "incremental": false
    },
    {
      "name": "OrigSystemId",
      "table": "HZ_ORIG_SYSTEMS_B",
      "column": "ORIG_SYSTEM_ID",
      "bicc": true,
      "pk": true,
      "incremental": false
    },
    {
      "name": "OrigSystemType",
      "table": "HZ_ORIG_SYSTEMS_B",
      "column": "ORIG_SYSTEM_TYPE",
      "bicc": false,
      "pk": false,
      "incremental": false
    },
    {
      "name": "SstFlag",
      "table": "HZ_ORIG_SYSTEMS_B",
      "column": "SST_FLAG",
      "bicc": false,
      "pk": false,
      "incremental": false
    },
    {
      "name": "StartDateActive",
      "table": "HZ_ORIG_SYSTEMS_B",
      "column": "START_DATE_ACTIVE",
      "bicc": false,
      "pk": false,
      "incremental": false
    },
    {
      "name": "Status",
      "table": "HZ_ORIG_SYSTEMS_B",
      "column": "STATUS",
      "bicc": true,
      "pk": false,
      "incremental": false
    }
  ],
  "by_table": {
    "HZ_ORIG_SYSTEMS_B": [
      {
        "attribute": "CreatedBy",
        "column": "CREATED_BY",
        "bicc": true,
        "pk": false
      },
      {
        "attribute": "CreatedByModule",
        "column": "CREATED_BY_MODULE",
        "bicc": false,
        "pk": false
      },
      {
        "attribute": "CreationDate",
        "column": "CREATION_DATE",
        "bicc": true,
        "pk": false
      },
      {
        "attribute": "EnableForItemsFlag",
        "column": "ENABLE_FOR_ITEMS_FLAG",
        "bicc": false,
        "pk": false
      },
      {
        "attribute": "EnableForPlanningFlag",
        "column": "ENABLE_FOR_PLANNING_FLAG",
        "bicc": false,
        "pk": false
      },
      {
        "attribute": "EnableForTcaFlag",
        "column": "ENABLE_FOR_TCA_FLAG",
        "bicc": false,
        "pk": false
      },
      {
        "attribute": "EndDateActive",
        "column": "END_DATE_ACTIVE",
        "bicc": false,
        "pk": false
      },
      {
        "attribute": "LastUpdateDate",
        "column": "LAST_UPDATE_DATE",
        "bicc": true,
        "pk": false
      },
      {
        "attribute": "LastUpdateLogin",
        "column": "LAST_UPDATE_LOGIN",
        "bicc": false,
        "pk": false
      },
      {
        "attribute": "LastUpdatedBy",
        "column": "LAST_UPDATED_BY",
        "bicc": true,
        "pk": false
      },
      {
        "attribute": "ObjectVersionNumber",
        "column": "OBJECT_VERSION_NUMBER",
        "bicc": false,
        "pk": false
      },
      {
        "attribute": "OrigSystem",
        "column": "ORIG_SYSTEM",
        "bicc": true,
        "pk": false
      },
      {
        "attribute": "OrigSystemId",
        "column": "ORIG_SYSTEM_ID",
        "bicc": true,
        "pk": true
      },
      {
        "attribute": "OrigSystemType",
        "column": "ORIG_SYSTEM_TYPE",
        "bicc": false,
        "pk": false
      },
      {
        "attribute": "SstFlag",
        "column": "SST_FLAG",
        "bicc": false,
        "pk": false
      },
      {
        "attribute": "StartDateActive",
        "column": "START_DATE_ACTIVE",
        "bicc": false,
        "pk": false
      },
      {
        "attribute": "Status",
        "column": "STATUS",
        "bicc": true,
        "pk": false
      }
    ]
  }
}