{
  "meta": {
    "pvo_name": "ProposalCostPVO",
    "full_path": "FscmTopModelAM.ConceptsAnalyticsAM.ProposalCostPVO",
    "module_path": "FscmTopModelAM.ConceptsAnalyticsAM",
    "module_code": "HCM",
    "type": "pvo",
    "description": "Extrai custos associados a propostas de produto, com detalhes de negócio e valores reais. Suporta análise financeira de conceitos e inovação de produtos."
  },
  "stats": {
    "total_attributes": 146,
    "tables_count": 5,
    "bicc_enabled": 145,
    "bicc_pct": 99,
    "pk_count": 1
  },
  "tables": [
    "ACD_BUSINESS_DETAILS_VL",
    "ACD_CONCEPT_B",
    "ACD_CONCEPT_TL",
    "ACD_COSTS",
    "ACD_PRODUCT_PROPOSAL"
  ],
  "attributes": [
    {
      "name": "BusinessDetailId",
      "table": "ACD_BUSINESS_DETAILS_VL",
      "column": "BUSINESS_DETAIL_ID",
      "bicc": true,
      "pk": false,
      "incremental": false
    },
    {
      "name": "BusinessDetalsActualCost",
      "table": "ACD_BUSINESS_DETAILS_VL",
      "column": "ACTUAL_COST",
      "bicc": true,
      "pk": false,
      "incremental": false
    },
    {
      "name": "BusinessDetalsActualDevFixedCost",
      "table": "ACD_BUSINESS_DETAILS_VL",
      "column": "ACTUAL_DEV_FIXED_COST",
      "bicc": true,
      "pk": false,
      "incremental": false
    },
    {
      "name": "BusinessDetalsActualDevLaborCost",
      "table": "ACD_BUSINESS_DETAILS_VL",
      "column": "ACTUAL_DEV_LABOR_COST",
      "bicc": true,
      "pk": false,
      "incremental": false
    },
    {
      "name": "BusinessDetalsActualDevMaterialCost",
      "table": "ACD_BUSINESS_DETAILS_VL",
      "column": "ACTUAL_DEV_MATERIAL_COST",
      "bicc": true,
      "pk": false,
      "incremental": false
    },
    {
      "name": "BusinessDetalsActualDevVariableCost",
      "table": "ACD_BUSINESS_DETAILS_VL",
      "column": "ACTUAL_DEV_VARIABLE_COST",
      "bicc": true,
      "pk": false,
      "incremental": false
    },
    {
      "name": "BusinessDetalsActualDevelopmentCost",
      "table": "ACD_BUSINESS_DETAILS_VL",
      "column": "ACTUAL_DEVELOPMENT_COST",
      "bicc": true,
      "pk": false,
      "incremental": false
    },
    {
      "name": "BusinessDetalsActualLaunch",
      "table": "ACD_BUSINESS_DETAILS_VL",
      "column": "ACTUAL_LAUNCH",
      "bicc": true,
      "pk": false,
      "incremental": false
    },
    {
      "name": "BusinessDetalsActualMargin",
      "table": "ACD_BUSINESS_DETAILS_VL",
      "column": "ACTUAL_MARGIN",
      "bicc": true,
      "pk": false,
      "incremental": false
    },
    {
      "name": "BusinessDetalsActualProdFixedCost",
      "table": "ACD_BUSINESS_DETAILS_VL",
      "column": "ACTUAL_PROD_FIXED_COST",
      "bicc": true,
      "pk": false,
      "incremental": false
    },
    {
      "name": "BusinessDetalsActualProdLaborCost",
      "table": "ACD_BUSINESS_DETAILS_VL",
      "column": "ACTUAL_PROD_LABOR_COST",
      "bicc": true,
      "pk": false,
      "incremental": false
    },
    {
      "name": "BusinessDetalsActualProdMaterialCost",
      "table": "ACD_BUSINESS_DETAILS_VL",
      "column": "ACTUAL_PROD_MATERIAL_COST",
      "bicc": true,
      "pk": false,
      "incremental": false
    },
    {
      "name": "BusinessDetalsActualProdVariableCost",
      "table": "ACD_BUSINESS_DETAILS_VL",
      "column": "ACTUAL_PROD_VARIABLE_COST",
      "bicc": true,
      "pk": false,
      "incremental": false
    },
    {
      "name": "BusinessDetalsActualProductionCost",
      "table": "ACD_BUSINESS_DETAILS_VL",
      "column": "ACTUAL_PRODUCTION_COST",
      "bicc": true,
      "pk": false,
      "incremental": false
    },
    {
      "name": "BusinessDetalsActualResources",
      "table": "ACD_BUSINESS_DETAILS_VL",
      "column": "ACTUAL_RESOURCES",
      "bicc": true,
      "pk": false,
      "incremental": false
    },
    {
      "name": "BusinessDetalsActualRevenue",
      "table": "ACD_BUSINESS_DETAILS_VL",
      "column": "ACTUAL_REVENUE",
      "bicc": true,
      "pk": false,
      "incremental": false
    },
    {
      "name": "BusinessDetalsAlignment",
      "table": "ACD_BUSINESS_DETAILS_VL",
      "column": "ALIGNMENT",
      "bicc": true,
      "pk": false,
      "incremental": false
    },
    {
      "name": "BusinessDetalsAllocatedBudget",
      "table": "ACD_BUSINESS_DETAILS_VL",
      "column": "ALLOCATED_BUDGET",
      "bicc": true,
      "pk": false,
      "incremental": false
    },
    {
      "name": "BusinessDetalsAverageSellingPrice",
      "table": "ACD_BUSINESS_DETAILS_VL",
      "column": "AVERAGE_SELLING_PRICE",
      "bicc": true,
      "pk": false,
      "incremental": false
    },
    {
      "name": "BusinessDetalsBaselineDate",
      "table": "ACD_BUSINESS_DETAILS_VL",
      "column": "BASELINE_DATE",
      "bicc": true,
      "pk": false,
      "incremental": false
    },
    {
      "name": "BusinessDetalsBreakEvenTime",
      "table": "ACD_BUSINESS_DETAILS_VL",
      "column": "BREAK_EVEN_TIME",
      "bicc": true,
      "pk": false,
      "incremental": false
    },
    {
      "name": "BusinessDetalsBusinessObjectives",
      "table": "ACD_BUSINESS_DETAILS_VL",
      "column": "BUSINESS_OBJECTIVES",
      "bicc": true,
      "pk": false,
      "incremental": false
    },
    {
      "name": "BusinessDetalsBusinessUnit",
      "table": "ACD_BUSINESS_DETAILS_VL",
      "column": "BUSINESS_UNIT",
      "bicc": true,
      "pk": false,
      "incremental": false
    },
    {
      "name": "BusinessDetalsBusinessUnitStrength",
      "table": "ACD_BUSINESS_DETAILS_VL",
      "column": "BUSINESS_UNIT_STRENGTH",
      "bicc": true,
      "pk": false,
      "incremental": false
    },
    {
      "name": "BusinessDetalsCompetitiveAdvantage",
      "table": "ACD_BUSINESS_DETAILS_VL",
      "column": "COMPETITIVE_ADVANTAGE",
      "bicc": true,
      "pk": false,
      "incremental": false
    },
    {
      "name": "BusinessDetalsCostValueIndex",
      "table": "ACD_BUSINESS_DETAILS_VL",
      "column": "COST_VALUE_INDEX",
      "bicc": true,
      "pk": false,
      "incremental": false
    },
    {
      "name": "BusinessDetalsCpi",
      "table": "ACD_BUSINESS_DETAILS_VL",
      "column": "CPI",
      "bicc": true,
      "pk": false,
      "incremental": false
    },
    {
      "name": "BusinessDetalsCreatedBy",
      "table": "ACD_BUSINESS_DETAILS_VL",
      "column": "CREATED_BY",
      "bicc": true,
      "pk": false,
      "incremental": false
    },
    {
      "name": "BusinessDetalsCreationDate",
      "table": "ACD_BUSINESS_DETAILS_VL",
      "column": "CREATION_DATE",
      "bicc": true,
      "pk": false,
      "incremental": false
    },
    {
      "name": "BusinessDetalsDevelopmentEnd",
      "table": "ACD_BUSINESS_DETAILS_VL",
      "column": "DEVELOPMENT_END",
      "bicc": true,
      "pk": false,
      "incremental": false
    },
    {
      "name": "BusinessDetalsDevelopmentStart",
      "table": "ACD_BUSINESS_DETAILS_VL",
      "column": "DEVELOPMENT_START",
      "bicc": true,
      "pk": false,
      "incremental": false
    },
    {
      "name": "BusinessDetalsDiscountRate",
      "table": "ACD_BUSINESS_DETAILS_VL",
      "column": "DISCOUNT_RATE",
      "bicc": true,
      "pk": false,
      "incremental": false
    },
    {
      "name": "BusinessDetalsEol",
      "table": "ACD_BUSINESS_DETAILS_VL",
      "column": "EOL",
      "bicc": true,
      "pk": false,
      "incremental": false
    },
    {
      "name": "BusinessDetalsExpectedCommercialValue",
      "table": "ACD_BUSINESS_DETAILS_VL",
      "column": "EXPECTED_COMMERCIAL_VALUE",
      "bicc": true,
      "pk": false,
      "incremental": false
    },
    {
      "name": "BusinessDetalsFundingAmount",
      "table": "ACD_BUSINESS_DETAILS_VL",
      "column": "FUNDING_AMOUNT",
      "bicc": true,
      "pk": false,
      "incremental": false
    },
    {
      "name": "BusinessDetalsFundingRequestFor",
      "table": "ACD_BUSINESS_DETAILS_VL",
      "column": "FUNDING_REQUEST_FOR",
      "bicc": true,
      "pk": false,
      "incremental": false
    },
    {
      "name": "BusinessDetalsHighLevelDesign",
      "table": "ACD_BUSINESS_DETAILS_VL",
      "column": "HIGH_LEVEL_DESIGN",
      "bicc": true,
      "pk": false,
      "incremental": false
    },
    {
      "name": "BusinessDetalsImpact",
      "table": "ACD_BUSINESS_DETAILS_VL",
      "column": "IMPACT",
      "bicc": true,
      "pk": false,
      "incremental": false
    },
    {
      "name": "BusinessDetalsInternalRateOfReturn",
      "table": "ACD_BUSINESS_DETAILS_VL",
      "column": "INTERNAL_RATE_OF_RETURN",
      "bicc": true,
      "pk": false,
      "incremental": false
    },
    {
      "name": "BusinessDetalsLastUpdateDate",
      "table": "ACD_BUSINESS_DETAILS_VL",
      "column": "LAST_UPDATE_DATE",
      "bicc": true,
      "pk": false,
      "incremental": false
    },
    {
      "name": "BusinessDetalsLastUpdateLogin",
      "table": "ACD_BUSINESS_DETAILS_VL",
      "column": "LAST_UPDATE_LOGIN",
      "bicc": true,
      "pk": false,
      "incremental": false
    },
    {
      "name": "BusinessDetalsLastUpdatedBy",
      "table": "ACD_BUSINESS_DETAILS_VL",
      "column": "LAST_UPDATED_BY",
      "bicc": true,
      "pk": false,
      "incremental": false
    },
    {
      "name": "BusinessDetalsLaunch",
      "table": "ACD_BUSINESS_DETAILS_VL",
      "column": "LAUNCH",
      "bicc": true,
      "pk": false,
      "incremental": false
    },
    {
      "name": "BusinessDetalsMarketAttractiveness",
      "table": "ACD_BUSINESS_DETAILS_VL",
      "column": "MARKET_ATTRACTIVENESS",
      "bicc": true,
      "pk": false,
      "incremental": false
    },
    {
      "name": "BusinessDetalsMarketGrowthPercent",
      "table": "ACD_BUSINESS_DETAILS_VL",
      "column": "MARKET_GROWTH_PERCENT",
      "bicc": true,
      "pk": false,
      "incremental": false
    },
    {
      "name": "BusinessDetalsMarketSharePercent",
      "table": "ACD_BUSINESS_DETAILS_VL",
      "column": "MARKET_SHARE_PERCENT",
      "bicc": true,
      "pk": false,
      "incremental": false
    },
    {
      "name": "BusinessDetalsMarketStrategy",
      "table": "ACD_BUSINESS_DETAILS_VL",
      "column": "MARKET_STRATEGY",
      "bicc": true,
      "pk": false,
      "incremental": false
    },
    {
      "name": "BusinessDetalsNetPresentValue",
      "table": "ACD_BUSINESS_DETAILS_VL",
      "column": "NET_PRESENT_VALUE",
      "bicc": true,
      "pk": false,
      "incremental": false
    },
    {
      "name": "BusinessDetalsObjectVersionNumber",
      "table": "ACD_BUSINESS_DETAILS_VL",
      "column": "OBJECT_VERSION_NUMBER",
      "bicc": true,
      "pk": false,
      "incremental": false
    },
    {
      "name": "BusinessDetalsPaybackPeriod",
      "table": "ACD_BUSINESS_DETAILS_VL",
      "column": "PAYBACK_PERIOD",
      "bicc": true,
      "pk": false,
      "incremental": false
    },
    {
      "name": "BusinessDetalsPrimaryJustification",
      "table": "ACD_BUSINESS_DETAILS_VL",
      "column": "PRIMARY_JUSTIFICATION",
      "bicc": true,
      "pk": false,
      "incremental": false
    },
    {
      "name": "BusinessDetalsProbOfCommercialSuccess",
      "table": "ACD_BUSINESS_DETAILS_VL",
      "column": "PROB_OF_COMMERCIAL_SUCCESS",
      "bicc": true,
      "pk": false,
      "incremental": false
    },
    {
      "name": "BusinessDetalsProbOfTechnicalSuccess",
      "table": "ACD_BUSINESS_DETAILS_VL",
      "column": "PROB_OF_TECHNICAL_SUCCESS",
      "bicc": true,
      "pk": false,
      "incremental": false
    },
    {
      "name": "BusinessDetalsProductCategorization",
      "table": "ACD_BUSINESS_DETAILS_VL",
      "column": "PRODUCT_CATEGORIZATION",
      "bicc": true,
      "pk": false,
      "incremental": false
    },
    {
      "name": "BusinessDetalsProductLine",
      "table": "ACD_BUSINESS_DETAILS_VL",
      "column": "PRODUCT_LINE",
      "bicc": true,
      "pk": false,
      "incremental": false
    },
    {
      "name": "BusinessDetalsProductProposalId",
      "table": "ACD_BUSINESS_DETAILS_VL",
      "column": "PRODUCT_PROPOSAL_ID",
      "bicc": true,
      "pk": false,
      "incremental": false
    },
    {
      "name": "BusinessDetalsProductStrategicFit",
      "table": "ACD_BUSINESS_DETAILS_VL",
      "column": "PRODUCT_STRATEGIC_FIT",
      "bicc": true,
      "pk": false,
      "incremental": false
    },
    {
      "name": "BusinessDetalsProjDevCost",
      "table": "ACD_BUSINESS_DETAILS_VL",
      "column": "PROJ_DEV_COST",
      "bicc": true,
      "pk": false,
      "incremental": false
    },
    {
      "name": "BusinessDetalsProjDevFixedCost",
      "table": "ACD_BUSINESS_DETAILS_VL",
      "column": "PROJ_DEV_FIXED_COST",
      "bicc": true,
      "pk": false,
      "incremental": false
    },
    {
      "name": "BusinessDetalsProjDevLaborCost",
      "table": "ACD_BUSINESS_DETAILS_VL",
      "column": "PROJ_DEV_LABOR_COST",
      "bicc": true,
      "pk": false,
      "incremental": false
    },
    {
      "name": "BusinessDetalsProjDevMaterialCost",
      "table": "ACD_BUSINESS_DETAILS_VL",
      "column": "PROJ_DEV_MATERIAL_COST",
      "bicc": true,
      "pk": false,
      "incremental": false
    },
    {
      "name": "BusinessDetalsProjDevVariableCost",
      "table": "ACD_BUSINESS_DETAILS_VL",
      "column": "PROJ_DEV_VARIABLE_COST",
      "bicc": true,
      "pk": false,
      "incremental": false
    },
    {
      "name": "BusinessDetalsProjProdCost",
      "table": "ACD_BUSINESS_DETAILS_VL",
      "column": "PROJ_PROD_COST",
      "bicc": true,
      "pk": false,
      "incremental": false
    },
    {
      "name": "BusinessDetalsProjProdFixedCost",
      "table": "ACD_BUSINESS_DETAILS_VL",
      "column": "PROJ_PROD_FIXED_COST",
      "bicc": true,
      "pk": false,
      "incremental": false
    },
    {
      "name": "BusinessDetalsProjProdLaborCost",
      "table": "ACD_BUSINESS_DETAILS_VL",
      "column": "PROJ_PROD_LABOR_COST",
      "bicc": true,
      "pk": false,
      "incremental": false
    },
    {
      "name": "BusinessDetalsProjProdMaterialCost",
      "table": "ACD_BUSINESS_DETAILS_VL",
      "column": "PROJ_PROD_MATERIAL_COST",
      "bicc": true,
      "pk": false,
      "incremental": false
    },
    {
      "name": "BusinessDetalsProjProdVariableCost",
      "table": "ACD_BUSINESS_DETAILS_VL",
      "column": "PROJ_PROD_VARIABLE_COST",
      "bicc": true,
      "pk": false,
      "incremental": false
    },
    {
      "name": "BusinessDetalsProjectedMargin",
      "table": "ACD_BUSINESS_DETAILS_VL",
      "column": "PROJECTED_MARGIN",
      "bicc": true,
      "pk": false,
      "incremental": false
    },
    {
      "name": "BusinessDetalsProjectedResources",
      "table": "ACD_BUSINESS_DETAILS_VL",
      "column": "PROJECTED_RESOURCES",
      "bicc": true,
      "pk": false,
      "incremental": false
    },
    {
      "name": "BusinessDetalsProposalProjectedCost",
      "table": "ACD_BUSINESS_DETAILS_VL",
      "column": "PROPOSAL_PROJECTED_COST",
      "bicc": true,
      "pk": false,
      "incremental": false
    },
    {
      "name": "BusinessDetalsProposalProjectedRevenue",
      "table": "ACD_BUSINESS_DETAILS_VL",
      "column": "PROPOSAL_PROJECTED_REVENUE",
      "bicc": true,
      "pk": false,
      "incremental": false
    },
    {
      "name": "BusinessDetalsProposalVersionNotes",
      "table": "ACD_BUSINESS_DETAILS_VL",
      "column": "PROPOSAL_VERSION_NOTES",
      "bicc": true,
      "pk": false,
      "incremental": false
    },
    {
      "name": "BusinessDetalsRequirementsDefinition",
      "table": "ACD_BUSINESS_DETAILS_VL",
      "column": "REQUIREMENTS_DEFINITION",
      "bicc": true,
      "pk": false,
      "incremental": false
    },
    {
      "name": "BusinessDetalsResourceValueIndex",
      "table": "ACD_BUSINESS_DETAILS_VL",
      "column": "RESOURCE_VALUE_INDEX",
      "bicc": true,
      "pk": false,
      "incremental": false
    },
    {
      "name": "BusinessDetalsReturnOnInvestment",
      "table": "ACD_BUSINESS_DETAILS_VL",
      "column": "RETURN_ON_INVESTMENT",
      "bicc": true,
      "pk": false,
      "incremental": false
    },
    {
      "name": "BusinessDetalsRiskNumberic",
      "table": "ACD_BUSINESS_DETAILS_VL",
      "column": "RISK_NUMBERIC",
      "bicc": true,
      "pk": false,
      "incremental": false
    },
    {
      "name": "BusinessDetalsRiskSubjective",
      "table": "ACD_BUSINESS_DETAILS_VL",
      "column": "RISK_SUBJECTIVE",
      "bicc": true,
      "pk": false,
      "incremental": false
    },
    {
      "name": "BusinessDetalsRndKnowHow",
      "table": "ACD_BUSINESS_DETAILS_VL",
      "column": "RND_KNOW_HOW",
      "bicc": true,
      "pk": false,
      "incremental": false
    },
    {
      "name": "BusinessDetalsRpi",
      "table": "ACD_BUSINESS_DETAILS_VL",
      "column": "RPI",
      "bicc": true,
      "pk": false,
      "incremental": false
    },
    {
      "name": "BusinessDetalsSecondaryJustification",
      "table": "ACD_BUSINESS_DETAILS_VL",
      "column": "SECONDARY_JUSTIFICATION",
      "bicc": true,
      "pk": false,
      "incremental": false
    },
    {
      "name": "BusinessDetalsSummary",
      "table": "ACD_BUSINESS_DETAILS_VL",
      "column": "SUMMARY",
      "bicc": true,
      "pk": false,
      "incremental": false
    },
    {
      "name": "BusinessDetalsSupplyChainFit",
      "table": "ACD_BUSINESS_DETAILS_VL",
      "column": "SUPPLY_CHAIN_FIT",
      "bicc": true,
      "pk": false,
      "incremental": false
    },
    {
      "name": "BusinessDetalsTargetCost",
      "table": "ACD_BUSINESS_DETAILS_VL",
      "column": "TARGET_COST",
      "bicc": true,
      "pk": false,
      "incremental": false
    },
    {
      "name": "BusinessDetalsYear2Revenue",
      "table": "ACD_BUSINESS_DETAILS_VL",
      "column": "YEAR_2_REVENUE",
      "bicc": true,
      "pk": false,
      "incremental": false
    },
    {
      "name": "BusinessDetalsYear3Revenue",
      "table": "ACD_BUSINESS_DETAILS_VL",
      "column": "YEAR_3_REVENUE",
      "bicc": true,
      "pk": false,
      "incremental": false
    },
    {
      "name": "BusinessDetalsYear5Revenue",
      "table": "ACD_BUSINESS_DETAILS_VL",
      "column": "YEAR_5_REVENUE",
      "bicc": true,
      "pk": false,
      "incremental": false
    },
    {
      "name": "ConceptAllowAccesstoEveryone",
      "table": "ACD_CONCEPT_B",
      "column": "ALLOW_ACCESSTO_EVERYONE",
      "bicc": true,
      "pk": false,
      "incremental": false
    },
    {
      "name": "ConceptConceptId",
      "table": "ACD_CONCEPT_B",
      "column": "CONCEPT_ID",
      "bicc": true,
      "pk": false,
      "incremental": false
    },
    {
      "name": "ConceptConceptNumber",
      "table": "ACD_CONCEPT_B",
      "column": "CONCEPT_NUMBER",
      "bicc": true,
      "pk": false,
      "incremental": false
    },
    {
      "name": "ConceptCreatedBy",
      "table": "ACD_CONCEPT_B",
      "column": "CREATED_BY",
      "bicc": true,
      "pk": false,
      "incremental": false
    },
    {
      "name": "ConceptCreationDate",
      "table": "ACD_CONCEPT_B",
      "column": "CREATION_DATE",
      "bicc": true,
      "pk": false,
      "incremental": false
    },
    {
      "name": "ConceptCurrencyCode",
      "table": "ACD_CONCEPT_B",
      "column": "CURRENCY_CODE",
      "bicc": true,
      "pk": false,
      "incremental": false
    },
    {
      "name": "ConceptDueDate",
      "table": "ACD_CONCEPT_B",
      "column": "DUE_DATE",
      "bicc": true,
      "pk": false,
      "incremental": false
    },
    {
      "name": "ConceptIsCurrent",
      "table": "ACD_CONCEPT_B",
      "column": "IS_CURRENT",
      "bicc": true,
      "pk": false,
      "incremental": false
    },
    {
      "name": "ConceptLastUpdateDate",
      "table": "ACD_CONCEPT_B",
      "column": "LAST_UPDATE_DATE",
      "bicc": true,
      "pk": false,
      "incremental": false
    },
    {
      "name": "ConceptLastUpdateLogin",
      "table": "ACD_CONCEPT_B",
      "column": "LAST_UPDATE_LOGIN",
      "bicc": true,
      "pk": false,
      "incremental": false
    },
    {
      "name": "ConceptLastUpdatedBy",
      "table": "ACD_CONCEPT_B",
      "column": "LAST_UPDATED_BY",
      "bicc": true,
      "pk": false,
      "incremental": false
    },
    {
      "name": "ConceptLifecyclePhase",
      "table": "ACD_CONCEPT_B",
      "column": "LIFECYCLE_PHASE",
      "bicc": true,
      "pk": false,
      "incremental": false
    },
    {
      "name": "ConceptMasterId",
      "table": "ACD_CONCEPT_B",
      "column": "MASTER_ID",
      "bicc": true,
      "pk": false,
      "incremental": false
    },
    {
      "name": "ConceptObjectVersionNumber",
      "table": "ACD_CONCEPT_B",
      "column": "OBJECT_VERSION_NUMBER",
      "bicc": true,
      "pk": false,
      "incremental": false
    },
    {
      "name": "ConceptPowerUnit",
      "table": "ACD_CONCEPT_B",
      "column": "POWER_UNIT",
      "bicc": true,
      "pk": false,
      "incremental": false
    },
    {
      "name": "ConceptTranslationConceptId",
      "table": "ACD_CONCEPT_TL",
      "column": "CONCEPT_ID",
      "bicc": true,
      "pk": false,
      "incremental": false
    },
    {
      "name": "ConceptTranslationCreatedBy",
      "table": "ACD_CONCEPT_TL",
      "column": "CREATED_BY",
      "bicc": true,
      "pk": false,
      "incremental": false
    },
    {
      "name": "ConceptTranslationCreationDate",
      "table": "ACD_CONCEPT_TL",
      "column": "CREATION_DATE",
      "bicc": true,
      "pk": false,
      "incremental": false
    },
    {
      "name": "ConceptTranslationDescription",
      "table": "ACD_CONCEPT_TL",
      "column": "DESCRIPTION",
      "bicc": false,
      "pk": false,
      "incremental": false
    },
    {
      "name": "ConceptTranslationLanguage",
      "table": "ACD_CONCEPT_TL",
      "column": "LANGUAGE",
      "bicc": true,
      "pk": false,
      "incremental": false
    },
    {
      "name": "ConceptTranslationLastUpdateDate",
      "table": "ACD_CONCEPT_TL",
      "column": "LAST_UPDATE_DATE",
      "bicc": true,
      "pk": false,
      "incremental": false
    },
    {
      "name": "ConceptTranslationLastUpdateLogin",
      "table": "ACD_CONCEPT_TL",
      "column": "LAST_UPDATE_LOGIN",
      "bicc": true,
      "pk": false,
      "incremental": false
    },
    {
      "name": "ConceptTranslationLastUpdatedBy",
      "table": "ACD_CONCEPT_TL",
      "column": "LAST_UPDATED_BY",
      "bicc": true,
      "pk": false,
      "incremental": false
    },
    {
      "name": "ConceptTranslationName",
      "table": "ACD_CONCEPT_TL",
      "column": "NAME",
      "bicc": true,
      "pk": false,
      "incremental": false
    },
    {
      "name": "ConceptTranslationObjectVersionNumber",
      "table": "ACD_CONCEPT_TL",
      "column": "OBJECT_VERSION_NUMBER",
      "bicc": true,
      "pk": false,
      "incremental": false
    },
    {
      "name": "ConceptTranslationSourceLang",
      "table": "ACD_CONCEPT_TL",
      "column": "SOURCE_LANG",
      "bicc": true,
      "pk": false,
      "incremental": false
    },
    {
      "name": "ConceptType",
      "table": "ACD_CONCEPT_B",
      "column": "TYPE",
      "bicc": true,
      "pk": false,
      "incremental": false
    },
    {
      "name": "ConceptVersion",
      "table": "ACD_CONCEPT_B",
      "column": "VERSION",
      "bicc": true,
      "pk": false,
      "incremental": false
    },
    {
      "name": "ConceptVolume",
      "table": "ACD_CONCEPT_B",
      "column": "VOLUME",
      "bicc": true,
      "pk": false,
      "incremental": false
    },
    {
      "name": "CostCostAmount",
      "table": "ACD_COSTS",
      "column": "COST_AMOUNT",
      "bicc": true,
      "pk": false,
      "incremental": false
    },
    {
      "name": "CostCostCategory",
      "table": "ACD_COSTS",
      "column": "COST_CATEGORY",
      "bicc": true,
      "pk": false,
      "incremental": false
    },
    {
      "name": "CostCostId",
      "table": "ACD_COSTS",
      "column": "COST_ID",
      "bicc": true,
      "pk": true,
      "incremental": false
    },
    {
      "name": "CostCostStatus",
      "table": "ACD_COSTS",
      "column": "COST_STATUS",
      "bicc": true,
      "pk": false,
      "incremental": false
    },
    {
      "name": "CostCostTrend",
      "table": "ACD_COSTS",
      "column": "COST_TREND",
      "bicc": true,
      "pk": false,
      "incremental": false
    },
    {
      "name": "CostCostType",
      "table": "ACD_COSTS",
      "column": "COST_TYPE",
      "bicc": true,
      "pk": false,
      "incremental": false
    },
    {
      "name": "CostCreatedBy",
      "table": "ACD_COSTS",
      "column": "CREATED_BY",
      "bicc": true,
      "pk": false,
      "incremental": false
    },
    {
      "name": "CostCreationDate",
      "table": "ACD_COSTS",
      "column": "CREATION_DATE",
      "bicc": true,
      "pk": false,
      "incremental": false
    },
    {
      "name": "CostEndDate",
      "table": "ACD_COSTS",
      "column": "END_DATE",
      "bicc": true,
      "pk": false,
      "incremental": false
    },
    {
      "name": "CostLastUpdateDate",
      "table": "ACD_COSTS",
      "column": "LAST_UPDATE_DATE",
      "bicc": true,
      "pk": false,
      "incremental": false
    },
    {
      "name": "CostLastUpdateLogin",
      "table": "ACD_COSTS",
      "column": "LAST_UPDATE_LOGIN",
      "bicc": true,
      "pk": false,
      "incremental": false
    },
    {
      "name": "CostLastUpdatedBy",
      "table": "ACD_COSTS",
      "column": "LAST_UPDATED_BY",
      "bicc": true,
      "pk": false,
      "incremental": false
    },
    {
      "name": "CostObjectVersionNumber",
      "table": "ACD_COSTS",
      "column": "OBJECT_VERSION_NUMBER",
      "bicc": true,
      "pk": false,
      "incremental": false
    },
    {
      "name": "CostProductProposalId",
      "table": "ACD_COSTS",
      "column": "PRODUCT_PROPOSAL_ID",
      "bicc": true,
      "pk": false,
      "incremental": false
    },
    {
      "name": "CostStartDate",
      "table": "ACD_COSTS",
      "column": "START_DATE",
      "bicc": true,
      "pk": false,
      "incremental": false
    },
    {
      "name": "ProposalAllowAccesstoEveryone",
      "table": "ACD_PRODUCT_PROPOSAL",
      "column": "ALLOW_ACCESSTO_EVERYONE",
      "bicc": true,
      "pk": false,
      "incremental": false
    },
    {
      "name": "ProposalConceptMasterId",
      "table": "ACD_PRODUCT_PROPOSAL",
      "column": "CONCEPT_MASTER_ID",
      "bicc": true,
      "pk": false,
      "incremental": false
    },
    {
      "name": "ProposalCreatedBy",
      "table": "ACD_PRODUCT_PROPOSAL",
      "column": "CREATED_BY",
      "bicc": true,
      "pk": false,
      "incremental": false
    },
    {
      "name": "ProposalCreationDate",
      "table": "ACD_PRODUCT_PROPOSAL",
      "column": "CREATION_DATE",
      "bicc": true,
      "pk": false,
      "incremental": false
    },
    {
      "name": "ProposalCurrencyConversionRate",
      "table": "ACD_PRODUCT_PROPOSAL",
      "column": "CURRENCY_CONVERSION_RATE",
      "bicc": true,
      "pk": false,
      "incremental": false
    },
    {
      "name": "ProposalIsCloned",
      "table": "ACD_PRODUCT_PROPOSAL",
      "column": "IS_CLONED",
      "bicc": true,
      "pk": false,
      "incremental": false
    },
    {
      "name": "ProposalIsLatest",
      "table": "ACD_PRODUCT_PROPOSAL",
      "column": "IS_LATEST",
      "bicc": true,
      "pk": false,
      "incremental": false
    },
    {
      "name": "ProposalLastUpdateDate",
      "table": "ACD_PRODUCT_PROPOSAL",
      "column": "LAST_UPDATE_DATE",
      "bicc": true,
      "pk": false,
      "incremental": false
    },
    {
      "name": "ProposalLastUpdateLogin",
      "table": "ACD_PRODUCT_PROPOSAL",
      "column": "LAST_UPDATE_LOGIN",
      "bicc": true,
      "pk": false,
      "incremental": false
    },
    {
      "name": "ProposalLastUpdatedBy",
      "table": "ACD_PRODUCT_PROPOSAL",
      "column": "LAST_UPDATED_BY",
      "bicc": true,
      "pk": false,
      "incremental": false
    },
    {
      "name": "ProposalObjectVersionNumber",
      "table": "ACD_PRODUCT_PROPOSAL",
      "column": "OBJECT_VERSION_NUMBER",
      "bicc": true,
      "pk": false,
      "incremental": false
    },
    {
      "name": "ProposalProductProposalId",
      "table": "ACD_PRODUCT_PROPOSAL",
      "column": "PRODUCT_PROPOSAL_ID",
      "bicc": true,
      "pk": false,
      "incremental": false
    },
    {
      "name": "ProposalProposalStatus",
      "table": "ACD_PRODUCT_PROPOSAL",
      "column": "PROPOSAL_STATUS",
      "bicc": true,
      "pk": false,
      "incremental": false
    },
    {
      "name": "ProposalPublishedFromPortfolio",
      "table": "ACD_PRODUCT_PROPOSAL",
      "column": "PUBLISHED_FROM_PORTFOLIO",
      "bicc": true,
      "pk": false,
      "incremental": false
    },
    {
      "name": "ProposalType",
      "table": "ACD_PRODUCT_PROPOSAL",
      "column": "PROPOSAL_TYPE",
      "bicc": true,
      "pk": false,
      "incremental": false
    },
    {
      "name": "ProposalVersion",
      "table": "ACD_PRODUCT_PROPOSAL",
      "column": "VERSION",
      "bicc": true,
      "pk": false,
      "incremental": false
    }
  ],
  "by_table": {
    "ACD_BUSINESS_DETAILS_VL": [
      {
        "attribute": "BusinessDetailId",
        "column": "BUSINESS_DETAIL_ID",
        "bicc": true,
        "pk": false
      },
      {
        "attribute": "BusinessDetalsActualCost",
        "column": "ACTUAL_COST",
        "bicc": true,
        "pk": false
      },
      {
        "attribute": "BusinessDetalsActualDevFixedCost",
        "column": "ACTUAL_DEV_FIXED_COST",
        "bicc": true,
        "pk": false
      },
      {
        "attribute": "BusinessDetalsActualDevLaborCost",
        "column": "ACTUAL_DEV_LABOR_COST",
        "bicc": true,
        "pk": false
      },
      {
        "attribute": "BusinessDetalsActualDevMaterialCost",
        "column": "ACTUAL_DEV_MATERIAL_COST",
        "bicc": true,
        "pk": false
      },
      {
        "attribute": "BusinessDetalsActualDevVariableCost",
        "column": "ACTUAL_DEV_VARIABLE_COST",
        "bicc": true,
        "pk": false
      },
      {
        "attribute": "BusinessDetalsActualDevelopmentCost",
        "column": "ACTUAL_DEVELOPMENT_COST",
        "bicc": true,
        "pk": false
      },
      {
        "attribute": "BusinessDetalsActualLaunch",
        "column": "ACTUAL_LAUNCH",
        "bicc": true,
        "pk": false
      },
      {
        "attribute": "BusinessDetalsActualMargin",
        "column": "ACTUAL_MARGIN",
        "bicc": true,
        "pk": false
      },
      {
        "attribute": "BusinessDetalsActualProdFixedCost",
        "column": "ACTUAL_PROD_FIXED_COST",
        "bicc": true,
        "pk": false
      },
      {
        "attribute": "BusinessDetalsActualProdLaborCost",
        "column": "ACTUAL_PROD_LABOR_COST",
        "bicc": true,
        "pk": false
      },
      {
        "attribute": "BusinessDetalsActualProdMaterialCost",
        "column": "ACTUAL_PROD_MATERIAL_COST",
        "bicc": true,
        "pk": false
      },
      {
        "attribute": "BusinessDetalsActualProdVariableCost",
        "column": "ACTUAL_PROD_VARIABLE_COST",
        "bicc": true,
        "pk": false
      },
      {
        "attribute": "BusinessDetalsActualProductionCost",
        "column": "ACTUAL_PRODUCTION_COST",
        "bicc": true,
        "pk": false
      },
      {
        "attribute": "BusinessDetalsActualResources",
        "column": "ACTUAL_RESOURCES",
        "bicc": true,
        "pk": false
      },
      {
        "attribute": "BusinessDetalsActualRevenue",
        "column": "ACTUAL_REVENUE",
        "bicc": true,
        "pk": false
      },
      {
        "attribute": "BusinessDetalsAlignment",
        "column": "ALIGNMENT",
        "bicc": true,
        "pk": false
      },
      {
        "attribute": "BusinessDetalsAllocatedBudget",
        "column": "ALLOCATED_BUDGET",
        "bicc": true,
        "pk": false
      },
      {
        "attribute": "BusinessDetalsAverageSellingPrice",
        "column": "AVERAGE_SELLING_PRICE",
        "bicc": true,
        "pk": false
      },
      {
        "attribute": "BusinessDetalsBaselineDate",
        "column": "BASELINE_DATE",
        "bicc": true,
        "pk": false
      },
      {
        "attribute": "BusinessDetalsBreakEvenTime",
        "column": "BREAK_EVEN_TIME",
        "bicc": true,
        "pk": false
      },
      {
        "attribute": "BusinessDetalsBusinessObjectives",
        "column": "BUSINESS_OBJECTIVES",
        "bicc": true,
        "pk": false
      },
      {
        "attribute": "BusinessDetalsBusinessUnit",
        "column": "BUSINESS_UNIT",
        "bicc": true,
        "pk": false
      },
      {
        "attribute": "BusinessDetalsBusinessUnitStrength",
        "column": "BUSINESS_UNIT_STRENGTH",
        "bicc": true,
        "pk": false
      },
      {
        "attribute": "BusinessDetalsCompetitiveAdvantage",
        "column": "COMPETITIVE_ADVANTAGE",
        "bicc": true,
        "pk": false
      },
      {
        "attribute": "BusinessDetalsCostValueIndex",
        "column": "COST_VALUE_INDEX",
        "bicc": true,
        "pk": false
      },
      {
        "attribute": "BusinessDetalsCpi",
        "column": "CPI",
        "bicc": true,
        "pk": false
      },
      {
        "attribute": "BusinessDetalsCreatedBy",
        "column": "CREATED_BY",
        "bicc": true,
        "pk": false
      },
      {
        "attribute": "BusinessDetalsCreationDate",
        "column": "CREATION_DATE",
        "bicc": true,
        "pk": false
      },
      {
        "attribute": "BusinessDetalsDevelopmentEnd",
        "column": "DEVELOPMENT_END",
        "bicc": true,
        "pk": false
      },
      {
        "attribute": "BusinessDetalsDevelopmentStart",
        "column": "DEVELOPMENT_START",
        "bicc": true,
        "pk": false
      },
      {
        "attribute": "BusinessDetalsDiscountRate",
        "column": "DISCOUNT_RATE",
        "bicc": true,
        "pk": false
      },
      {
        "attribute": "BusinessDetalsEol",
        "column": "EOL",
        "bicc": true,
        "pk": false
      },
      {
        "attribute": "BusinessDetalsExpectedCommercialValue",
        "column": "EXPECTED_COMMERCIAL_VALUE",
        "bicc": true,
        "pk": false
      },
      {
        "attribute": "BusinessDetalsFundingAmount",
        "column": "FUNDING_AMOUNT",
        "bicc": true,
        "pk": false
      },
      {
        "attribute": "BusinessDetalsFundingRequestFor",
        "column": "FUNDING_REQUEST_FOR",
        "bicc": true,
        "pk": false
      },
      {
        "attribute": "BusinessDetalsHighLevelDesign",
        "column": "HIGH_LEVEL_DESIGN",
        "bicc": true,
        "pk": false
      },
      {
        "attribute": "BusinessDetalsImpact",
        "column": "IMPACT",
        "bicc": true,
        "pk": false
      },
      {
        "attribute": "BusinessDetalsInternalRateOfReturn",
        "column": "INTERNAL_RATE_OF_RETURN",
        "bicc": true,
        "pk": false
      },
      {
        "attribute": "BusinessDetalsLastUpdateDate",
        "column": "LAST_UPDATE_DATE",
        "bicc": true,
        "pk": false
      },
      {
        "attribute": "BusinessDetalsLastUpdateLogin",
        "column": "LAST_UPDATE_LOGIN",
        "bicc": true,
        "pk": false
      },
      {
        "attribute": "BusinessDetalsLastUpdatedBy",
        "column": "LAST_UPDATED_BY",
        "bicc": true,
        "pk": false
      },
      {
        "attribute": "BusinessDetalsLaunch",
        "column": "LAUNCH",
        "bicc": true,
        "pk": false
      },
      {
        "attribute": "BusinessDetalsMarketAttractiveness",
        "column": "MARKET_ATTRACTIVENESS",
        "bicc": true,
        "pk": false
      },
      {
        "attribute": "BusinessDetalsMarketGrowthPercent",
        "column": "MARKET_GROWTH_PERCENT",
        "bicc": true,
        "pk": false
      },
      {
        "attribute": "BusinessDetalsMarketSharePercent",
        "column": "MARKET_SHARE_PERCENT",
        "bicc": true,
        "pk": false
      },
      {
        "attribute": "BusinessDetalsMarketStrategy",
        "column": "MARKET_STRATEGY",
        "bicc": true,
        "pk": false
      },
      {
        "attribute": "BusinessDetalsNetPresentValue",
        "column": "NET_PRESENT_VALUE",
        "bicc": true,
        "pk": false
      },
      {
        "attribute": "BusinessDetalsObjectVersionNumber",
        "column": "OBJECT_VERSION_NUMBER",
        "bicc": true,
        "pk": false
      },
      {
        "attribute": "BusinessDetalsPaybackPeriod",
        "column": "PAYBACK_PERIOD",
        "bicc": true,
        "pk": false
      },
      {
        "attribute": "BusinessDetalsPrimaryJustification",
        "column": "PRIMARY_JUSTIFICATION",
        "bicc": true,
        "pk": false
      },
      {
        "attribute": "BusinessDetalsProbOfCommercialSuccess",
        "column": "PROB_OF_COMMERCIAL_SUCCESS",
        "bicc": true,
        "pk": false
      },
      {
        "attribute": "BusinessDetalsProbOfTechnicalSuccess",
        "column": "PROB_OF_TECHNICAL_SUCCESS",
        "bicc": true,
        "pk": false
      },
      {
        "attribute": "BusinessDetalsProductCategorization",
        "column": "PRODUCT_CATEGORIZATION",
        "bicc": true,
        "pk": false
      },
      {
        "attribute": "BusinessDetalsProductLine",
        "column": "PRODUCT_LINE",
        "bicc": true,
        "pk": false
      },
      {
        "attribute": "BusinessDetalsProductProposalId",
        "column": "PRODUCT_PROPOSAL_ID",
        "bicc": true,
        "pk": false
      },
      {
        "attribute": "BusinessDetalsProductStrategicFit",
        "column": "PRODUCT_STRATEGIC_FIT",
        "bicc": true,
        "pk": false
      },
      {
        "attribute": "BusinessDetalsProjDevCost",
        "column": "PROJ_DEV_COST",
        "bicc": true,
        "pk": false
      },
      {
        "attribute": "BusinessDetalsProjDevFixedCost",
        "column": "PROJ_DEV_FIXED_COST",
        "bicc": true,
        "pk": false
      },
      {
        "attribute": "BusinessDetalsProjDevLaborCost",
        "column": "PROJ_DEV_LABOR_COST",
        "bicc": true,
        "pk": false
      },
      {
        "attribute": "BusinessDetalsProjDevMaterialCost",
        "column": "PROJ_DEV_MATERIAL_COST",
        "bicc": true,
        "pk": false
      },
      {
        "attribute": "BusinessDetalsProjDevVariableCost",
        "column": "PROJ_DEV_VARIABLE_COST",
        "bicc": true,
        "pk": false
      },
      {
        "attribute": "BusinessDetalsProjProdCost",
        "column": "PROJ_PROD_COST",
        "bicc": true,
        "pk": false
      },
      {
        "attribute": "BusinessDetalsProjProdFixedCost",
        "column": "PROJ_PROD_FIXED_COST",
        "bicc": true,
        "pk": false
      },
      {
        "attribute": "BusinessDetalsProjProdLaborCost",
        "column": "PROJ_PROD_LABOR_COST",
        "bicc": true,
        "pk": false
      },
      {
        "attribute": "BusinessDetalsProjProdMaterialCost",
        "column": "PROJ_PROD_MATERIAL_COST",
        "bicc": true,
        "pk": false
      },
      {
        "attribute": "BusinessDetalsProjProdVariableCost",
        "column": "PROJ_PROD_VARIABLE_COST",
        "bicc": true,
        "pk": false
      },
      {
        "attribute": "BusinessDetalsProjectedMargin",
        "column": "PROJECTED_MARGIN",
        "bicc": true,
        "pk": false
      },
      {
        "attribute": "BusinessDetalsProjectedResources",
        "column": "PROJECTED_RESOURCES",
        "bicc": true,
        "pk": false
      },
      {
        "attribute": "BusinessDetalsProposalProjectedCost",
        "column": "PROPOSAL_PROJECTED_COST",
        "bicc": true,
        "pk": false
      },
      {
        "attribute": "BusinessDetalsProposalProjectedRevenue",
        "column": "PROPOSAL_PROJECTED_REVENUE",
        "bicc": true,
        "pk": false
      },
      {
        "attribute": "BusinessDetalsProposalVersionNotes",
        "column": "PROPOSAL_VERSION_NOTES",
        "bicc": true,
        "pk": false
      },
      {
        "attribute": "BusinessDetalsRequirementsDefinition",
        "column": "REQUIREMENTS_DEFINITION",
        "bicc": true,
        "pk": false
      },
      {
        "attribute": "BusinessDetalsResourceValueIndex",
        "column": "RESOURCE_VALUE_INDEX",
        "bicc": true,
        "pk": false
      },
      {
        "attribute": "BusinessDetalsReturnOnInvestment",
        "column": "RETURN_ON_INVESTMENT",
        "bicc": true,
        "pk": false
      },
      {
        "attribute": "BusinessDetalsRiskNumberic",
        "column": "RISK_NUMBERIC",
        "bicc": true,
        "pk": false
      },
      {
        "attribute": "BusinessDetalsRiskSubjective",
        "column": "RISK_SUBJECTIVE",
        "bicc": true,
        "pk": false
      },
      {
        "attribute": "BusinessDetalsRndKnowHow",
        "column": "RND_KNOW_HOW",
        "bicc": true,
        "pk": false
      },
      {
        "attribute": "BusinessDetalsRpi",
        "column": "RPI",
        "bicc": true,
        "pk": false
      },
      {
        "attribute": "BusinessDetalsSecondaryJustification",
        "column": "SECONDARY_JUSTIFICATION",
        "bicc": true,
        "pk": false
      },
      {
        "attribute": "BusinessDetalsSummary",
        "column": "SUMMARY",
        "bicc": true,
        "pk": false
      },
      {
        "attribute": "BusinessDetalsSupplyChainFit",
        "column": "SUPPLY_CHAIN_FIT",
        "bicc": true,
        "pk": false
      },
      {
        "attribute": "BusinessDetalsTargetCost",
        "column": "TARGET_COST",
        "bicc": true,
        "pk": false
      },
      {
        "attribute": "BusinessDetalsYear2Revenue",
        "column": "YEAR_2_REVENUE",
        "bicc": true,
        "pk": false
      },
      {
        "attribute": "BusinessDetalsYear3Revenue",
        "column": "YEAR_3_REVENUE",
        "bicc": true,
        "pk": false
      },
      {
        "attribute": "BusinessDetalsYear5Revenue",
        "column": "YEAR_5_REVENUE",
        "bicc": true,
        "pk": false
      }
    ],
    "ACD_CONCEPT_B": [
      {
        "attribute": "ConceptAllowAccesstoEveryone",
        "column": "ALLOW_ACCESSTO_EVERYONE",
        "bicc": true,
        "pk": false
      },
      {
        "attribute": "ConceptConceptId",
        "column": "CONCEPT_ID",
        "bicc": true,
        "pk": false
      },
      {
        "attribute": "ConceptConceptNumber",
        "column": "CONCEPT_NUMBER",
        "bicc": true,
        "pk": false
      },
      {
        "attribute": "ConceptCreatedBy",
        "column": "CREATED_BY",
        "bicc": true,
        "pk": false
      },
      {
        "attribute": "ConceptCreationDate",
        "column": "CREATION_DATE",
        "bicc": true,
        "pk": false
      },
      {
        "attribute": "ConceptCurrencyCode",
        "column": "CURRENCY_CODE",
        "bicc": true,
        "pk": false
      },
      {
        "attribute": "ConceptDueDate",
        "column": "DUE_DATE",
        "bicc": true,
        "pk": false
      },
      {
        "attribute": "ConceptIsCurrent",
        "column": "IS_CURRENT",
        "bicc": true,
        "pk": false
      },
      {
        "attribute": "ConceptLastUpdateDate",
        "column": "LAST_UPDATE_DATE",
        "bicc": true,
        "pk": false
      },
      {
        "attribute": "ConceptLastUpdateLogin",
        "column": "LAST_UPDATE_LOGIN",
        "bicc": true,
        "pk": false
      },
      {
        "attribute": "ConceptLastUpdatedBy",
        "column": "LAST_UPDATED_BY",
        "bicc": true,
        "pk": false
      },
      {
        "attribute": "ConceptLifecyclePhase",
        "column": "LIFECYCLE_PHASE",
        "bicc": true,
        "pk": false
      },
      {
        "attribute": "ConceptMasterId",
        "column": "MASTER_ID",
        "bicc": true,
        "pk": false
      },
      {
        "attribute": "ConceptObjectVersionNumber",
        "column": "OBJECT_VERSION_NUMBER",
        "bicc": true,
        "pk": false
      },
      {
        "attribute": "ConceptPowerUnit",
        "column": "POWER_UNIT",
        "bicc": true,
        "pk": false
      },
      {
        "attribute": "ConceptType",
        "column": "TYPE",
        "bicc": true,
        "pk": false
      },
      {
        "attribute": "ConceptVersion",
        "column": "VERSION",
        "bicc": true,
        "pk": false
      },
      {
        "attribute": "ConceptVolume",
        "column": "VOLUME",
        "bicc": true,
        "pk": false
      }
    ],
    "ACD_CONCEPT_TL": [
      {
        "attribute": "ConceptTranslationConceptId",
        "column": "CONCEPT_ID",
        "bicc": true,
        "pk": false
      },
      {
        "attribute": "ConceptTranslationCreatedBy",
        "column": "CREATED_BY",
        "bicc": true,
        "pk": false
      },
      {
        "attribute": "ConceptTranslationCreationDate",
        "column": "CREATION_DATE",
        "bicc": true,
        "pk": false
      },
      {
        "attribute": "ConceptTranslationDescription",
        "column": "DESCRIPTION",
        "bicc": false,
        "pk": false
      },
      {
        "attribute": "ConceptTranslationLanguage",
        "column": "LANGUAGE",
        "bicc": true,
        "pk": false
      },
      {
        "attribute": "ConceptTranslationLastUpdateDate",
        "column": "LAST_UPDATE_DATE",
        "bicc": true,
        "pk": false
      },
      {
        "attribute": "ConceptTranslationLastUpdateLogin",
        "column": "LAST_UPDATE_LOGIN",
        "bicc": true,
        "pk": false
      },
      {
        "attribute": "ConceptTranslationLastUpdatedBy",
        "column": "LAST_UPDATED_BY",
        "bicc": true,
        "pk": false
      },
      {
        "attribute": "ConceptTranslationName",
        "column": "NAME",
        "bicc": true,
        "pk": false
      },
      {
        "attribute": "ConceptTranslationObjectVersionNumber",
        "column": "OBJECT_VERSION_NUMBER",
        "bicc": true,
        "pk": false
      },
      {
        "attribute": "ConceptTranslationSourceLang",
        "column": "SOURCE_LANG",
        "bicc": true,
        "pk": false
      }
    ],
    "ACD_COSTS": [
      {
        "attribute": "CostCostAmount",
        "column": "COST_AMOUNT",
        "bicc": true,
        "pk": false
      },
      {
        "attribute": "CostCostCategory",
        "column": "COST_CATEGORY",
        "bicc": true,
        "pk": false
      },
      {
        "attribute": "CostCostId",
        "column": "COST_ID",
        "bicc": true,
        "pk": true
      },
      {
        "attribute": "CostCostStatus",
        "column": "COST_STATUS",
        "bicc": true,
        "pk": false
      },
      {
        "attribute": "CostCostTrend",
        "column": "COST_TREND",
        "bicc": true,
        "pk": false
      },
      {
        "attribute": "CostCostType",
        "column": "COST_TYPE",
        "bicc": true,
        "pk": false
      },
      {
        "attribute": "CostCreatedBy",
        "column": "CREATED_BY",
        "bicc": true,
        "pk": false
      },
      {
        "attribute": "CostCreationDate",
        "column": "CREATION_DATE",
        "bicc": true,
        "pk": false
      },
      {
        "attribute": "CostEndDate",
        "column": "END_DATE",
        "bicc": true,
        "pk": false
      },
      {
        "attribute": "CostLastUpdateDate",
        "column": "LAST_UPDATE_DATE",
        "bicc": true,
        "pk": false
      },
      {
        "attribute": "CostLastUpdateLogin",
        "column": "LAST_UPDATE_LOGIN",
        "bicc": true,
        "pk": false
      },
      {
        "attribute": "CostLastUpdatedBy",
        "column": "LAST_UPDATED_BY",
        "bicc": true,
        "pk": false
      },
      {
        "attribute": "CostObjectVersionNumber",
        "column": "OBJECT_VERSION_NUMBER",
        "bicc": true,
        "pk": false
      },
      {
        "attribute": "CostProductProposalId",
        "column": "PRODUCT_PROPOSAL_ID",
        "bicc": true,
        "pk": false
      },
      {
        "attribute": "CostStartDate",
        "column": "START_DATE",
        "bicc": true,
        "pk": false
      }
    ],
    "ACD_PRODUCT_PROPOSAL": [
      {
        "attribute": "ProposalAllowAccesstoEveryone",
        "column": "ALLOW_ACCESSTO_EVERYONE",
        "bicc": true,
        "pk": false
      },
      {
        "attribute": "ProposalConceptMasterId",
        "column": "CONCEPT_MASTER_ID",
        "bicc": true,
        "pk": false
      },
      {
        "attribute": "ProposalCreatedBy",
        "column": "CREATED_BY",
        "bicc": true,
        "pk": false
      },
      {
        "attribute": "ProposalCreationDate",
        "column": "CREATION_DATE",
        "bicc": true,
        "pk": false
      },
      {
        "attribute": "ProposalCurrencyConversionRate",
        "column": "CURRENCY_CONVERSION_RATE",
        "bicc": true,
        "pk": false
      },
      {
        "attribute": "ProposalIsCloned",
        "column": "IS_CLONED",
        "bicc": true,
        "pk": false
      },
      {
        "attribute": "ProposalIsLatest",
        "column": "IS_LATEST",
        "bicc": true,
        "pk": false
      },
      {
        "attribute": "ProposalLastUpdateDate",
        "column": "LAST_UPDATE_DATE",
        "bicc": true,
        "pk": false
      },
      {
        "attribute": "ProposalLastUpdateLogin",
        "column": "LAST_UPDATE_LOGIN",
        "bicc": true,
        "pk": false
      },
      {
        "attribute": "ProposalLastUpdatedBy",
        "column": "LAST_UPDATED_BY",
        "bicc": true,
        "pk": false
      },
      {
        "attribute": "ProposalObjectVersionNumber",
        "column": "OBJECT_VERSION_NUMBER",
        "bicc": true,
        "pk": false
      },
      {
        "attribute": "ProposalProductProposalId",
        "column": "PRODUCT_PROPOSAL_ID",
        "bicc": true,
        "pk": false
      },
      {
        "attribute": "ProposalProposalStatus",
        "column": "PROPOSAL_STATUS",
        "bicc": true,
        "pk": false
      },
      {
        "attribute": "ProposalPublishedFromPortfolio",
        "column": "PUBLISHED_FROM_PORTFOLIO",
        "bicc": true,
        "pk": false
      },
      {
        "attribute": "ProposalType",
        "column": "PROPOSAL_TYPE",
        "bicc": true,
        "pk": false
      },
      {
        "attribute": "ProposalVersion",
        "column": "VERSION",
        "bicc": true,
        "pk": false
      }
    ]
  }
}